stackholm/__init__.py
stackholm/__version__.py
stackholm/context.py
stackholm/exceptions.py
stackholm/py.typed
stackholm/state.py
stackholm/storage.py
stackholm/storages/__init__.py
stackholm/storages/_discovery.py
stackholm/storages/asgiref_local/__init__.py
stackholm/storages/asgiref_local/asgiref_local_storage.py
stackholm/storages/contextvar/__init__.py
stackholm/storages/contextvar/contextvar_storage.py
stackholm/storages/optimized_list/__init__.py
stackholm/storages/optimized_list/optimized_list_state.py
stackholm/storages/optimized_list/optimized_list_storage.py
stackholm/storages/thread_local/__init__.py
stackholm/storages/thread_local/thread_local_storage.py
stackholm-1.0.0a9.dist-info/LICENSE
stackholm-1.0.0a9.dist-info/METADATA
stackholm-1.0.0a9.dist-info/WHEEL
stackholm-1.0.0a9.dist-info/top_level.txt
stackholm-1.0.0a9.dist-info/zip-safe
stackholm-1.0.0a9.dist-info/RECORD
